{"id":"jobs.html","dependencies":[{"name":"/home/saheel/projects/techyon/pccetechyon/package.json","includedInParent":true,"mtime":1539165137727},{"name":"./index.js","dynamic":true,"parent":"/home/saheel/projects/techyon/pccetechyon/jobs.html","resolved":"/home/saheel/projects/techyon/pccetechyon/index.js"}],"generated":{"html":"<!DOCTYPE html>\n<html lang=\"en\">\n<head>\n    <meta charset=\"UTF-8\">\n    <meta name=\"viewport\" content=\"width=device-width, initial-scale=1.0\">\n    <meta http-equiv=\"X-UA-Compatible\" content=\"ie=edge\">\n    <title>Jobs</title>\n</head>\n<body>\n    <section id=\"FEE1\"> \n        <h5>Front End ENgineer</h5>\n        <h6>Company</h6>\n        <div id=\"exp\"></div>\n        <div id=\"skills\"></div>\n    </section>\n    <script src=\"/c96ad7ef2a167bde3be88fb706cd381c.js\"></script>\n</body>\n</html>"},"hash":"6c67bb4ff3b44bb28a017c19e33faf0e","cacheData":{}}